MANIFEST.in
README.txt
license.txt
readme.txt
setup.py
django_quickview.egg-info/PKG-INFO
django_quickview.egg-info/SOURCES.txt
django_quickview.egg-info/dependency_links.txt
django_quickview.egg-info/top_level.txt
docs/basic.html
docs/basic.md
docs/getting_started.rst
docs/help_generator.py
docs/examplesite/manage.py
docs/examplesite/test.db
docs/examplesite/examplesite/__init__.py
docs/examplesite/examplesite/settings.py
docs/examplesite/examplesite/urls.py
docs/examplesite/examplesite/wsgi.py
docs/examplesite/examplesite/__pycache__/__init__.cpython-33.pyc
docs/examplesite/examplesite/__pycache__/settings.cpython-33.pyc
docs/examplesite/examplesite/__pycache__/urls.cpython-33.pyc
docs/examplesite/examplesite/__pycache__/wsgi.cpython-33.pyc
docs/examplesite/friendslist/__init__.py
docs/examplesite/friendslist/models.py
docs/examplesite/friendslist/views.py
docs/examplesite/friendslist/__pycache__/__init__.cpython-33.pyc
docs/examplesite/friendslist/__pycache__/models.cpython-33.pyc
docs/examplesite/friendslist/__pycache__/views.cpython-33.pyc
docs/examplesite/friendslist/management/__init__.py
docs/examplesite/friendslist/management/__pycache__/__init__.cpython-33.pyc
docs/examplesite/friendslist/management/commands/__init__.py
docs/examplesite/friendslist/management/commands/testdata.py
docs/examplesite/friendslist/management/commands/__pycache__/__init__.cpython-33.pyc
docs/examplesite/friendslist/management/commands/__pycache__/testdata.cpython-33.pyc
docs/examplesite/friendslist/static/css/bootstrap.min.css
docs/examplesite/friendslist/static/css/bootswatch.less
docs/examplesite/friendslist/templates/base_site.html
docs/examplesite/friendslist/templates/index.html
docs/examplesite/friendslist/templates/friendslist/Spew/add.html
docs/examplesite/friendslist/templates/friendslist/Spew/delete.html
docs/examplesite/friendslist/templates/friendslist/Spew/detail.html
docs/examplesite/friendslist/templates/friendslist/Spew/index.html
docs/examplesite/friendslist/templates/friendslist/Spew/update.html
docs/examplesite/friendslist/templates/friendslist/friend/add.html
