Metadata-Version: 1.1
Name: django-quickview
Version: 0.3
Summary: Putting the nitro in rapid web development.
Home-page: https://bitbucket.org/weholt/django-quickview
Author: Thomas A. Weholt
Author-email: thomas@weholt.org
License: BSD License
Platform: UNKNOWN
Classifier: Environment :: Web Environment
Classifier: Framework :: Django
Classifier: Intended Audience :: Developers
Classifier: License :: OSI Approved :: BSD License
Classifier: Operating System :: OS Independent
Classifier: Programming Language :: Python
Classifier: Programming Language :: Python :: 3.3
Classifier: Programming Language :: Python :: 2.7
Classifier: Topic :: Internet :: WWW/HTTP
Classifier: Topic :: Internet :: WWW/HTTP :: Dynamic Content
